[
 {
  "id": "city-13292",
  "markers": {
   "items": [
    "tree"
   ]
  }
 },
 {
  "id": "city-13293"
 },
 {
  "id": "city-13294",
  "colors": {
   "hexPalette": [
    "#ffe700",
    "#0090d3",
    "#e20015",
    "#181500",
    "#666868",
    "#ffffff"
   ],
   "byNames": {
    "gold": [
     {
      "distanceToThreshold": 26,
      "matcherColor": "#ffff00"
     }
    ],
    "blue": [
     {
      "distanceToThreshold": 20.465205198458406,
      "matcherColor": "#1d7dc0"
     }
    ],
    "red": [
     {
      "distanceToThreshold": 44.194972420063685,
      "matcherColor": "#f00"
     }
    ],
    "grey": [
     {
      "distanceToThreshold": -1,
      "matcherColor": "#888"
     }
    ],
    "white": [
     {
      "distanceToThreshold": -1,
      "matcherColor": "#fff"
     }
    ]
   },
   "byNamesRejected": {
    "red": [
     {
      "distanceToThreshold": -151.95258136093247,
      "matcherColor": "#f00"
     }
    ],
    "blue": [
     {
      "distanceToThreshold": -73.1052215354454,
      "matcherColor": "#243b7f"
     }
    ],
    "green": [
     {
      "distanceToThreshold": -3.1450481775601418,
      "matcherColor": "#006f00"
     }
    ],
    "gold": [
     {
      "distanceToThreshold": -160.64451046876286,
      "matcherColor": "#b68f5e"
     }
    ]
   }
  }
 },
 {
  "id": "city-13295",
  "colors": {
   "hexPalette": [
    "#008dfd",
    "#002c4b",
    "#7f8193",
    "#ffffff"
   ],
   "byNames": {
    "blue": [
     {
      "distanceToThreshold": 47.83447493940356,
      "matcherColor": "#0099ff"
     }
    ],
    "grey": [
     {
      "distanceToThreshold": -1,
      "matcherColor": "#888"
     }
    ],
    "white": [
     {
      "distanceToThreshold": -1,
      "matcherColor": "#fff"
     }
    ]
   },
   "byNamesRejected": {
    "red": [
     {
      "distanceToThreshold": -189.41789101691074,
      "matcherColor": "#f00"
     }
    ],
    "green": [
     {
      "distanceToThreshold": -10.568384694197007,
      "matcherColor": "#006f00"
     }
    ],
    "gold": [
     {
      "distanceToThreshold": -148.05287789405847,
      "matcherColor": "#b68f5e"
     }
    ],
    "blue": [
     {
      "distanceToThreshold": -5,
      "matcherColor": "#243b7f"
     }
    ]
   }
  },
  "markers": {
   "animals": [
    "fish",
    "mermaid"
   ]
  }
 },
 {
  "id": "city-13296",
  "colors": {
   "hexPalette": [
    "#e3e3e3"
   ],
   "byNames": {
    "grey": [
     {
      "distanceToThreshold": -1,
      "matcherColor": "#888"
     }
    ]
   },
   "byNamesRejected": {}
  }
 },
 {
  "id": "gemeinde-13297",
  "colors": {
   "hexPalette": [
    "#f4c33f",
    "#487540",
    "#ffffff"
   ],
   "byNames": {
    "gold": [
     {
      "distanceToThreshold": 41.318458307730594,
      "matcherColor": "#e6c633"
     }
    ],
    "white": [
     {
      "distanceToThreshold": -1,
      "matcherColor": "#fff"
     }
    ]
   },
   "byNamesRejected": {
    "red": [
     {
      "distanceToThreshold": -146.4376293816909,
      "matcherColor": "#f00"
     }
    ],
    "blue": [
     {
      "distanceToThreshold": -32.89241088485109,
      "matcherColor": "#243b7f"
     }
    ],
    "green": [
     {
      "distanceToThreshold": -6.5194280961092375,
      "matcherColor": "#006f00"
     }
    ],
    "gold": [
     {
      "distanceToThreshold": -56.944431248349744,
      "matcherColor": "#b68f5e"
     }
    ]
   }
  }
 },
 {
  "id": "gemeinde-13298",
  "colors": {
   "hexPalette": [
    "#903e2f",
    "#0090c8",
    "#000000",
    "#ffffff"
   ],
   "byNames": {
    "blue": [
     {
      "distanceToThreshold": 24.41910625068561,
      "matcherColor": "#1d7dc0"
     }
    ],
    "black": [
     {
      "distanceToThreshold": -1,
      "matcherColor": "#000"
     }
    ],
    "white": [
     {
      "distanceToThreshold": -1,
      "matcherColor": "#fff"
     }
    ]
   },
   "byNamesRejected": {
    "red": [
     {
      "distanceToThreshold": -270.96677557497935,
      "matcherColor": "#fe3940"
     }
    ],
    "blue": [
     {
      "distanceToThreshold": -74.43585831168707,
      "matcherColor": "#243b7f"
     }
    ],
    "green": [
     {
      "distanceToThreshold": -66.77539193392383,
      "matcherColor": "#00824a"
     }
    ],
    "gold": [
     {
      "distanceToThreshold": -150.6205118216172,
      "matcherColor": "#b68f5e"
     }
    ]
   }
  }
 },
 {
  "id": "gemeinde-13299",
  "colors": {
   "hexPalette": [
    "#e6e7a7",
    "#101501",
    "#458152"
   ],
   "byNames": {
    "black": [
     {
      "distanceToThreshold": -1,
      "matcherColor": "#000"
     }
    ]
   },
   "byNamesRejected": {
    "red": [
     {
      "distanceToThreshold": -160.75090861718465,
      "matcherColor": "#f00"
     }
    ],
    "blue": [
     {
      "distanceToThreshold": -29.52094726934027,
      "matcherColor": "#243b7f"
     }
    ],
    "green": [
     {
      "distanceToThreshold": -7.037303048377481,
      "matcherColor": "#07923f"
     }
    ],
    "gold": [
     {
      "distanceToThreshold": -54.49454135459908,
      "matcherColor": "#b68f5e"
     }
    ]
   }
  }
 },
 {
  "id": "city-13300",
  "colors": {
   "hexPalette": [
    "#de4426",
    "#717878",
    "#17181f",
    "#e7e7e7"
   ],
   "byNames": {
    "grey": [
     {
      "distanceToThreshold": -1,
      "matcherColor": "#888"
     }
    ]
   },
   "byNamesRejected": {
    "red": [
     {
      "distanceToThreshold": -4.599054368237475,
      "matcherColor": "#f00"
     }
    ],
    "blue": [
     {
      "distanceToThreshold": -143.92409428196868,
      "matcherColor": "#5596c3"
     }
    ],
    "green": [
     {
      "distanceToThreshold": -139.2967509582288,
      "matcherColor": "#006f00"
     }
    ],
    "gold": [
     {
      "distanceToThreshold": -41.78899744078434,
      "matcherColor": "#b68f5e"
     }
    ]
   }
  }
 },
 {
  "id": "gemeinde-13301",
  "colors": {
   "hexPalette": [
    "#f00534",
    "#0a7f36",
    "#999d9e",
    "#ffffff"
   ],
   "byNames": {
    "red": [
     {
      "distanceToThreshold": 25.64928703319523,
      "matcherColor": "#f00"
     }
    ],
    "green": [
     {
      "distanceToThreshold": 38.763239418404694,
      "matcherColor": "#07923f"
     }
    ],
    "grey": [
     {
      "distanceToThreshold": -1,
      "matcherColor": "#888"
     }
    ],
    "white": [
     {
      "distanceToThreshold": -1,
      "matcherColor": "#fff"
     }
    ]
   },
   "byNamesRejected": {
    "blue": [
     {
      "distanceToThreshold": -43.0970416646375,
      "matcherColor": "#243b7f"
     }
    ],
    "green": [
     {
      "distanceToThreshold": -177.46962444359923,
      "matcherColor": "#006f00"
     }
    ],
    "gold": [
     {
      "distanceToThreshold": -117.313282074412,
      "matcherColor": "#b68f5e"
     }
    ],
    "red": [
     {
      "distanceToThreshold": -201.19388329051543,
      "matcherColor": "#f00"
     }
    ]
   }
  },
  "markers": {
   "animals": [
    "bird"
   ],
   "items": [
    "walls"
   ]
  }
 },
 {
  "id": "gemeinde-13302",
  "colors": {
   "hexPalette": [
    "#e20015",
    "#616161",
    "#0d0d0d",
    "#ffffff"
   ],
   "byNames": {
    "red": [
     {
      "distanceToThreshold": 44.194972420063685,
      "matcherColor": "#f00"
     }
    ],
    "grey": [
     {
      "distanceToThreshold": -1,
      "matcherColor": "#888"
     }
    ],
    "black": [
     {
      "distanceToThreshold": -1,
      "matcherColor": "#000"
     }
    ],
    "white": [
     {
      "distanceToThreshold": -1,
      "matcherColor": "#fff"
     }
    ]
   },
   "byNamesRejected": {
    "blue": [
     {
      "distanceToThreshold": -164.5573423426631,
      "matcherColor": "#2e3192"
     }
    ],
    "green": [
     {
      "distanceToThreshold": -162.66182932924394,
      "matcherColor": "#006f00"
     }
    ],
    "gold": [
     {
      "distanceToThreshold": -106.47522338173931,
      "matcherColor": "#b68f5e"
     }
    ]
   }
  },
  "markers": {
   "items": [
    "walls"
   ]
  }
 },
 {
  "id": "city-13303",
  "colors": {
   "hexPalette": [
    "#e8372f",
    "#428642",
    "#0f0a00",
    "#ffffff"
   ],
   "byNames": {
    "red": [
     {
      "distanceToThreshold": 4.085574493381031,
      "matcherColor": "#f00"
     }
    ],
    "black": [
     {
      "distanceToThreshold": -1,
      "matcherColor": "#000"
     }
    ],
    "white": [
     {
      "distanceToThreshold": -1,
      "matcherColor": "#fff"
     }
    ]
   },
   "byNamesRejected": {
    "blue": [
     {
      "distanceToThreshold": -41.22252713699653,
      "matcherColor": "#243b7f"
     }
    ],
    "green": [
     {
      "distanceToThreshold": -0.28266749240614075,
      "matcherColor": "#07923f"
     }
    ],
    "gold": [
     {
      "distanceToThreshold": -59.670380629460695,
      "matcherColor": "#b68f5e"
     }
    ],
    "red": [
     {
      "distanceToThreshold": -160.90039435418117,
      "matcherColor": "#f00"
     }
    ]
   }
  },
  "markers": {
   "animals": [
    "bird"
   ],
   "items": [
    "sword"
   ]
  }
 },
 {
  "id": "city-13304",
  "colors": {
   "hexPalette": [
    "#fbca0e",
    "#0191c9",
    "#0d1721",
    "#636365",
    "#ffffff"
   ],
   "byNames": {
    "gold": [
     {
      "distanceToThreshold": 17.268278761557006,
      "matcherColor": "#e6c633"
     }
    ],
    "blue": [
     {
      "distanceToThreshold": 24.433161512442524,
      "matcherColor": "#1d7dc0"
     }
    ],
    "black": [
     {
      "distanceToThreshold": -1,
      "matcherColor": "#000"
     }
    ],
    "grey": [
     {
      "distanceToThreshold": -1,
      "matcherColor": "#888"
     }
    ],
    "white": [
     {
      "distanceToThreshold": -1,
      "matcherColor": "#fff"
     }
    ]
   },
   "byNamesRejected": {
    "red": [
     {
      "distanceToThreshold": -270.8687421451421,
      "matcherColor": "#fe3940"
     }
    ],
    "blue": [
     {
      "distanceToThreshold": -171.0398374760468,
      "matcherColor": "#5596c3"
     }
    ],
    "green": [
     {
      "distanceToThreshold": -67.88666857808127,
      "matcherColor": "#00824a"
     }
    ],
    "gold": [
     {
      "distanceToThreshold": -150.2712533847649,
      "matcherColor": "#b68f5e"
     }
    ]
   }
  }
 },
 {
  "id": "gemeinde-13305",
  "colors": {
   "hexPalette": [
    "#0746a3",
    "#008500",
    "#99a8a1",
    "#ffffff"
   ],
   "byNames": {
    "blue": [
     {
      "distanceToThreshold": 18.696247143873236,
      "matcherColor": "#0059c7"
     }
    ],
    "green": [
     {
      "distanceToThreshold": 68,
      "matcherColor": "#006f00"
     }
    ],
    "grey": [
     {
      "distanceToThreshold": -1,
      "matcherColor": "#888"
     }
    ],
    "white": [
     {
      "distanceToThreshold": -1,
      "matcherColor": "#fff"
     }
    ]
   },
   "byNamesRejected": {
    "red": [
     {
      "distanceToThreshold": -207.60041724587256,
      "matcherColor": "#f00"
     }
    ],
    "green": [
     {
      "distanceToThreshold": -47.56393447619885,
      "matcherColor": "#00824a"
     }
    ],
    "gold": [
     {
      "distanceToThreshold": -145.085348087083,
      "matcherColor": "#b68f5e"
     }
    ],
    "blue": [
     {
      "distanceToThreshold": -91.33076356114773,
      "matcherColor": "#243b7f"
     }
    ]
   }
  }
 },
 {
  "id": "gemeinde-13306",
  "colors": {
   "hexPalette": [
    "#009300",
    "#61786a",
    "#ffffff"
   ],
   "byNames": {
    "green": [
     {
      "distanceToThreshold": 54,
      "matcherColor": "#006f00"
     }
    ],
    "white": [
     {
      "distanceToThreshold": -1,
      "matcherColor": "#fff"
     }
    ]
   },
   "byNamesRejected": {
    "red": [
     {
      "distanceToThreshold": -144.3043315583408,
      "matcherColor": "#fe3940"
     }
    ],
    "blue": [
     {
      "distanceToThreshold": -14.683683916501693,
      "matcherColor": "#5596c3"
     }
    ],
    "gold": [
     {
      "distanceToThreshold": -28.870692581975533,
      "matcherColor": "#b68f5e"
     }
    ],
    "green": [
     {
      "distanceToThreshold": -42.63040485158382,
      "matcherColor": "#00824a"
     }
    ]
   }
  },
  "markers": {
   "animals": [
    "horse"
   ]
  }
 },
 {
  "id": "city-13307",
  "colors": {
   "hexPalette": [
    "#f4cb15",
    "#788172",
    "#1a1c20",
    "#ffffff"
   ],
   "byNames": {
    "gold": [
     {
      "distanceToThreshold": 26.518661914433586,
      "matcherColor": "#e6c633"
     }
    ],
    "grey": [
     {
      "distanceToThreshold": -1,
      "matcherColor": "#888"
     }
    ],
    "white": [
     {
      "distanceToThreshold": -1,
      "matcherColor": "#fff"
     }
    ]
   },
   "byNamesRejected": {
    "red": [
     {
      "distanceToThreshold": -122.52868582663393,
      "matcherColor": "#fe3940"
     }
    ],
    "blue": [
     {
      "distanceToThreshold": -161.5905627295901,
      "matcherColor": "#5596c3"
     }
    ],
    "green": [
     {
      "distanceToThreshold": -160.36173829081793,
      "matcherColor": "#0f0"
     }
    ]
   }
  }
 },
 {
  "id": "city-13308",
  "colors": {
   "hexPalette": [
    "#00824d",
    "#aad4e8"
   ],
   "byNames": {
    "green": [
     {
      "distanceToThreshold": 57,
      "matcherColor": "#00824a"
     }
    ]
   },
   "byNamesRejected": {
    "red": [
     {
      "distanceToThreshold": -213.52617929085162,
      "matcherColor": "#fe3940"
     }
    ],
    "blue": [
     {
      "distanceToThreshold": -31.52578177264664,
      "matcherColor": "#5596c3"
     }
    ],
    "gold": [
     {
      "distanceToThreshold": -94.75464451834716,
      "matcherColor": "#b68f5e"
     }
    ],
    "green": [
     {
      "distanceToThreshold": -183.89751946258085,
      "matcherColor": "#07923f"
     }
    ]
   }
  }
 },
 {
  "id": "gemeinde-13309",
  "colors": {
   "hexPalette": [
    "#019499",
    "#0e1822",
    "#e6ffff"
   ],
   "byNames": {
    "blue": [
     {
      "distanceToThreshold": 6.764673383175342,
      "matcherColor": "#1d7dc0"
     }
    ],
    "black": [
     {
      "distanceToThreshold": -1,
      "matcherColor": "#000"
     }
    ]
   },
   "byNamesRejected": {
    "red": [
     {
      "distanceToThreshold": -246.1539425755135,
      "matcherColor": "#fe3940"
     }
    ],
    "green": [
     {
      "distanceToThreshold": -253.4020966738555,
      "matcherColor": "#0f0"
     }
    ],
    "gold": [
     {
      "distanceToThreshold": -141.91334775095973,
      "matcherColor": "#b68f5e"
     }
    ],
    "blue": [
     {
      "distanceToThreshold": -108.81207588499205,
      "matcherColor": "#5596c3"
     }
    ]
   }
  }
 },
 {
  "id": "city-13310",
  "colors": {
   "hexPalette": [
    "#f32212",
    "#202300",
    "#686163",
    "#fdfdfd"
   ],
   "byNames": {
    "red": [
     {
      "distanceToThreshold": 39.70111664078023,
      "matcherColor": "#f00"
     }
    ],
    "green": [
     {
      "distanceToThreshold": 7.537887487646785,
      "matcherColor": "#006f00"
     }
    ],
    "grey": [
     {
      "distanceToThreshold": -1,
      "matcherColor": "#888"
     }
    ],
    "white": [
     {
      "distanceToThreshold": -1,
      "matcherColor": "#fff"
     }
    ]
   },
   "byNamesRejected": {
    "blue": [
     {
      "distanceToThreshold": -69.30970574554718,
      "matcherColor": "#243b7f"
     }
    ],
    "green": [
     {
      "distanceToThreshold": -165.54256005605015,
      "matcherColor": "#006f00"
     }
    ],
    "gold": [
     {
      "distanceToThreshold": -147.3644135332772,
      "matcherColor": "#b68f5e"
     }
    ],
    "red": [
     {
      "distanceToThreshold": -145.72992712531496,
      "matcherColor": "#f00"
     }
    ]
   }
  },
  "markers": {
   "items": [
    "tree"
   ]
  }
 },
 {
  "id": "gemeinde-13311",
  "colors": {
   "hexPalette": [
    "#497451",
    "#a8a5a9",
    "#ffffff"
   ],
   "byNames": {
    "grey": [
     {
      "distanceToThreshold": -1,
      "matcherColor": "#888"
     }
    ],
    "white": [
     {
      "distanceToThreshold": -1,
      "matcherColor": "#fff"
     }
    ]
   },
   "byNamesRejected": {
    "red": [
     {
      "distanceToThreshold": -150.52331769259266,
      "matcherColor": "#f00"
     }
    ],
    "blue": [
     {
      "distanceToThreshold": -22.06095295571457,
      "matcherColor": "#243b7f"
     }
    ],
    "green": [
     {
      "distanceToThreshold": -14.659225819720362,
      "matcherColor": "#00824a"
     }
    ],
    "gold": [
     {
      "distanceToThreshold": -53.04423912787418,
      "matcherColor": "#b68f5e"
     }
    ]
   }
  }
 },
 {
  "id": "city-13312",
  "colors": {
   "hexPalette": [
    "#ffdd00",
    "#ed1d26",
    "#857578",
    "#1a1818",
    "#ffffff"
   ],
   "byNames": {
    "gold": [
     {
      "distanceToThreshold": 16,
      "matcherColor": "#ffff00"
     }
    ],
    "red": [
     {
      "distanceToThreshold": 28.921628843511463,
      "matcherColor": "#f00"
     }
    ],
    "grey": [
     {
      "distanceToThreshold": -1,
      "matcherColor": "#888"
     }
    ],
    "white": [
     {
      "distanceToThreshold": -1,
      "matcherColor": "#fff"
     }
    ]
   },
   "byNamesRejected": {
    "red": [
     {
      "distanceToThreshold": -141,
      "matcherColor": "#f00"
     }
    ],
    "blue": [
     {
      "distanceToThreshold": -160.32929900492127,
      "matcherColor": "#2e3192"
     }
    ],
    "green": [
     {
      "distanceToThreshold": -163.64739304790814,
      "matcherColor": "#006f00"
     }
    ],
    "gold": [
     {
      "distanceToThreshold": -78.4088147481944,
      "matcherColor": "#b68f5e"
     }
    ]
   }
  }
 },
 {
  "id": "gemeinde-13313",
  "colors": {
   "hexPalette": [
    "#e44018",
    "#22a134",
    "#a1a0a3",
    "#020403",
    "#ffffff"
   ],
   "byNames": {
    "red": [
     {
      "distanceToThreshold": 6.508503893307491,
      "matcherColor": "#f00"
     }
    ],
    "green": [
     {
      "distanceToThreshold": 27.212807378489998,
      "matcherColor": "#07923f"
     }
    ],
    "grey": [
     {
      "distanceToThreshold": -1,
      "matcherColor": "#888"
     }
    ],
    "black": [
     {
      "distanceToThreshold": -1,
      "matcherColor": "#000"
     }
    ],
    "white": [
     {
      "distanceToThreshold": -1,
      "matcherColor": "#fff"
     }
    ]
   },
   "byNamesRejected": {
    "blue": [
     {
      "distanceToThreshold": -66.62148316932637,
      "matcherColor": "#243b7f"
     }
    ],
    "green": [
     {
      "distanceToThreshold": -144.02777612924496,
      "matcherColor": "#006f00"
     }
    ],
    "gold": [
     {
      "distanceToThreshold": -94.89351180730586,
      "matcherColor": "#b68f5e"
     }
    ],
    "red": [
     {
      "distanceToThreshold": -198.32714563980278,
      "matcherColor": "#f00"
     }
    ]
   }
  },
  "markers": {
   "items": [
    "cross",
    "flower",
    "rose",
    "heart"
   ]
  }
 },
 {
  "id": "city-13314",
  "colors": {
   "hexPalette": [
    "#f1cb3b",
    "#2946ac",
    "#000003",
    "#ffffff"
   ],
   "byNames": {
    "gold": [
     {
      "distanceToThreshold": 45.50862325381056,
      "matcherColor": "#e6c633"
     }
    ],
    "blue": [
     {
      "distanceToThreshold": 26.206509502568395,
      "matcherColor": "#2e3192"
     }
    ],
    "black": [
     {
      "distanceToThreshold": -1,
      "matcherColor": "#000"
     }
    ],
    "white": [
     {
      "distanceToThreshold": -1,
      "matcherColor": "#fff"
     }
    ]
   },
   "byNamesRejected": {
    "red": [
     {
      "distanceToThreshold": -203.3372548748223,
      "matcherColor": "#f00"
     }
    ],
    "blue": [
     {
      "distanceToThreshold": -133.63754351705134,
      "matcherColor": "#5596c3"
     }
    ],
    "green": [
     {
      "distanceToThreshold": -62.00409829181969,
      "matcherColor": "#00824a"
     }
    ],
    "gold": [
     {
      "distanceToThreshold": -116.90110231425919,
      "matcherColor": "#b68f5e"
     }
    ]
   }
  }
 },
 {
  "id": "city-13315",
  "colors": {
   "hexPalette": [
    "#fef502",
    "#442500",
    "#797468",
    "#ffffff"
   ],
   "byNames": {
    "gold": [
     {
      "distanceToThreshold": 39.753049234040404,
      "matcherColor": "#ffff00"
     }
    ],
    "grey": [
     {
      "distanceToThreshold": -1,
      "matcherColor": "#888"
     }
    ],
    "white": [
     {
      "distanceToThreshold": -1,
      "matcherColor": "#fff"
     }
    ]
   },
   "byNamesRejected": {
    "red": [
     {
      "distanceToThreshold": -110.62528688503002,
      "matcherColor": "#f00"
     }
    ],
    "blue": [
     {
      "distanceToThreshold": -72.80436739806413,
      "matcherColor": "#243b7f"
     }
    ],
    "green": [
     {
      "distanceToThreshold": -10.4987562112089,
      "matcherColor": "#006f00"
     }
    ],
    "gold": [
     {
      "distanceToThreshold": -121.8460887673969,
      "matcherColor": "#b68f5e"
     }
    ]
   }
  }
 },
 {
  "id": "gemeinde-13316",
  "colors": {
   "hexPalette": [
    "#f7c705",
    "#c34232",
    "#479670",
    "#12131e",
    "#ffffff"
   ],
   "byNames": {
    "gold": [
     {
      "distanceToThreshold": 10.949006126277112,
      "matcherColor": "#e6c633"
     }
    ],
    "black": [
     {
      "distanceToThreshold": -1,
      "matcherColor": "#000"
     }
    ],
    "white": [
     {
      "distanceToThreshold": -1,
      "matcherColor": "#fff"
     }
    ]
   },
   "byNamesRejected": {
    "red": [
     {
      "distanceToThreshold": -180.81271308913037,
      "matcherColor": "#fe3940"
     }
    ],
    "blue": [
     {
      "distanceToThreshold": -4.172442046075858,
      "matcherColor": "#5596c3"
     }
    ],
    "green": [
     {
      "distanceToThreshold": -20.703159789440704,
      "matcherColor": "#07923f"
     }
    ],
    "gold": [
     {
      "distanceToThreshold": -52.66765285564442,
      "matcherColor": "#b68f5e"
     }
    ]
   }
  }
 },
 {
  "id": "gemeinde-13317",
  "colors": {
   "hexPalette": [
    "#f3c857",
    "#3c373b",
    "#ffffff"
   ],
   "byNames": {
    "gold": [
     {
      "distanceToThreshold": 21.6724642065264,
      "matcherColor": "#e6c633"
     }
    ],
    "grey": [
     {
      "distanceToThreshold": -1,
      "matcherColor": "#888"
     }
    ],
    "white": [
     {
      "distanceToThreshold": -1,
      "matcherColor": "#fff"
     }
    ]
   },
   "byNamesRejected": {
    "red": [
     {
      "distanceToThreshold": -115.25494828060076,
      "matcherColor": "#fe3940"
     }
    ],
    "blue": [
     {
      "distanceToThreshold": -117.80798770524916,
      "matcherColor": "#5596c3"
     }
    ],
    "green": [
     {
      "distanceToThreshold": -173.899602121716,
      "matcherColor": "#0f0"
     }
    ]
   }
  }
 },
 {
  "id": "gemeinde-13318",
  "colors": {
   "hexPalette": [
    "#d24830",
    "#22a134",
    "#aaaca9",
    "#ffffff"
   ],
   "byNames": {
    "green": [
     {
      "distanceToThreshold": 27.212807378489998,
      "matcherColor": "#07923f"
     }
    ],
    "grey": [
     {
      "distanceToThreshold": -1,
      "matcherColor": "#888"
     }
    ],
    "white": [
     {
      "distanceToThreshold": -1,
      "matcherColor": "#fff"
     }
    ]
   },
   "byNamesRejected": {
    "red": [
     {
      "distanceToThreshold": -198.32714563980278,
      "matcherColor": "#f00"
     }
    ],
    "blue": [
     {
      "distanceToThreshold": -66.62148316932637,
      "matcherColor": "#243b7f"
     }
    ],
    "green": [
     {
      "distanceToThreshold": -128.91779278989637,
      "matcherColor": "#006f00"
     }
    ],
    "gold": [
     {
      "distanceToThreshold": -94.89351180730586,
      "matcherColor": "#b68f5e"
     }
    ]
   }
  }
 },
 {
  "id": "city-13319",
  "colors": {
   "hexPalette": [
    "#f1d218",
    "#0090c8",
    "#565658",
    "#000000",
    "#ffffff"
   ],
   "byNames": {
    "gold": [
     {
      "distanceToThreshold": 28.47223445913111,
      "matcherColor": "#e6c633"
     }
    ],
    "blue": [
     {
      "distanceToThreshold": 24.41910625068561,
      "matcherColor": "#1d7dc0"
     }
    ],
    "grey": [
     {
      "distanceToThreshold": -1,
      "matcherColor": "#888"
     }
    ],
    "black": [
     {
      "distanceToThreshold": -1,
      "matcherColor": "#000"
     }
    ],
    "white": [
     {
      "distanceToThreshold": -1,
      "matcherColor": "#fff"
     }
    ]
   },
   "byNamesRejected": {
    "red": [
     {
      "distanceToThreshold": -270.96677557497935,
      "matcherColor": "#fe3940"
     }
    ],
    "blue": [
     {
      "distanceToThreshold": -159.11712611187014,
      "matcherColor": "#5596c3"
     }
    ],
    "green": [
     {
      "distanceToThreshold": -66.77539193392383,
      "matcherColor": "#00824a"
     }
    ],
    "gold": [
     {
      "distanceToThreshold": -150.6205118216172,
      "matcherColor": "#b68f5e"
     }
    ]
   }
  }
 },
 {
  "id": "gemeinde-13320",
  "colors": {
   "hexPalette": [
    "#fffd01",
    "#fc0325",
    "#5b4d4f",
    "#050208",
    "#a1a0a5",
    "#ffffff"
   ],
   "byNames": {
    "gold": [
     {
      "distanceToThreshold": 47.763932022500214,
      "matcherColor": "#ffff00"
     }
    ],
    "red": [
     {
      "distanceToThreshold": 42.757551100927856,
      "matcherColor": "#f00"
     }
    ],
    "grey": [
     {
      "distanceToThreshold": -1,
      "matcherColor": "#888"
     }
    ],
    "black": [
     {
      "distanceToThreshold": -1,
      "matcherColor": "#000"
     }
    ],
    "white": [
     {
      "distanceToThreshold": -1,
      "matcherColor": "#fff"
     }
    ]
   },
   "byNamesRejected": {
    "red": [
     {
      "distanceToThreshold": -173.00197627686626,
      "matcherColor": "#f00"
     }
    ],
    "blue": [
     {
      "distanceToThreshold": -177.55630911428136,
      "matcherColor": "#2e3192"
     }
    ],
    "green": [
     {
      "distanceToThreshold": -186.65321252427196,
      "matcherColor": "#006f00"
     }
    ],
    "gold": [
     {
      "distanceToThreshold": -106.58031096140985,
      "matcherColor": "#b68f5e"
     }
    ]
   }
  }
 },
 {
  "id": "city-13321",
  "colors": {
   "hexPalette": [
    "#e44018",
    "#6b6b6d",
    "#ffffff",
    "#1a1b24"
   ],
   "byNames": {
    "red": [
     {
      "distanceToThreshold": 6.508503893307491,
      "matcherColor": "#f00"
     }
    ],
    "grey": [
     {
      "distanceToThreshold": -1,
      "matcherColor": "#888"
     }
    ],
    "white": [
     {
      "distanceToThreshold": -1,
      "matcherColor": "#fff"
     }
    ]
   },
   "byNamesRejected": {
    "blue": [
     {
      "distanceToThreshold": -157.9403588140572,
      "matcherColor": "#243b7f"
     }
    ],
    "green": [
     {
      "distanceToThreshold": -144.02777612924496,
      "matcherColor": "#006f00"
     }
    ],
    "gold": [
     {
      "distanceToThreshold": -55.139046374372924,
      "matcherColor": "#b68f5e"
     }
    ]
   }
  },
  "markers": {
   "animals": [
    "lion"
   ]
  }
 },
 {
  "id": "gemeinde-13322",
  "colors": {
   "hexPalette": [
    "#f9d229",
    "#5b8054",
    "#0f0c02",
    "#ffffff"
   ],
   "byNames": {
    "gold": [
     {
      "distanceToThreshold": 35.40325224750231,
      "matcherColor": "#e6c633"
     }
    ],
    "black": [
     {
      "distanceToThreshold": -1,
      "matcherColor": "#000"
     }
    ],
    "white": [
     {
      "distanceToThreshold": -1,
      "matcherColor": "#fff"
     }
    ]
   },
   "byNamesRejected": {
    "red": [
     {
      "distanceToThreshold": -144.35685859808254,
      "matcherColor": "#f00"
     }
    ],
    "blue": [
     {
      "distanceToThreshold": -33.3181362359971,
      "matcherColor": "#5596c3"
     }
    ],
    "green": [
     {
      "distanceToThreshold": -28.436417837902056,
      "matcherColor": "#07923f"
     }
    ],
    "gold": [
     {
      "distanceToThreshold": -32.76852914647294,
      "matcherColor": "#b68f5e"
     }
    ]
   }
  },
  "markers": {
   "animals": [
    "boar",
    "wolf"
   ]
  }
 },
 {
  "id": "kreis-13323",
  "colors": {
   "hexPalette": [
    "#fdd017",
    "#005ebe",
    "#88866b",
    "#2b2b29",
    "#ffffff"
   ],
   "byNames": {
    "gold": [
     {
      "distanceToThreshold": 11.358453971938765,
      "matcherColor": "#b68f5e"
     }
    ],
    "blue": [
     {
      "distanceToThreshold": 49.704369859013,
      "matcherColor": "#0059c7"
     }
    ],
    "grey": [
     {
      "distanceToThreshold": -1,
      "matcherColor": "#888"
     }
    ],
    "white": [
     {
      "distanceToThreshold": -1,
      "matcherColor": "#fff"
     }
    ]
   },
   "byNamesRejected": {
    "red": [
     {
      "distanceToThreshold": -117.31598691248686,
      "matcherColor": "#fe3940"
     }
    ],
    "blue": [
     {
      "distanceToThreshold": -22.96115772464877,
      "matcherColor": "#5596c3"
     }
    ],
    "green": [
     {
      "distanceToThreshold": -76.82470537150812,
      "matcherColor": "#07923f"
     }
    ],
    "gold": [
     {
      "distanceToThreshold": -151.52068456772733,
      "matcherColor": "#b68f5e"
     }
    ]
   }
  },
  "markers": {
   "animals": [
    "rooster",
    "lion",
    "bird"
   ],
   "items": [
    "cross"
   ]
  }
 },
 {
  "id": "kreis-13324",
  "colors": {
   "hexPalette": [
    "#c22835",
    "#858585",
    "#ffffff"
   ],
   "byNames": {
    "grey": [
     {
      "distanceToThreshold": -1,
      "matcherColor": "#888"
     }
    ],
    "white": [
     {
      "distanceToThreshold": -1,
      "matcherColor": "#fff"
     }
    ]
   },
   "byNamesRejected": {
    "red": [
     {
      "distanceToThreshold": -10.166512630798806,
      "matcherColor": "#f00"
     }
    ],
    "blue": [
     {
      "distanceToThreshold": -115.025712396779,
      "matcherColor": "#2e3192"
     }
    ],
    "green": [
     {
      "distanceToThreshold": -123.27447104611466,
      "matcherColor": "#006f00"
     }
    ],
    "gold": [
     {
      "distanceToThreshold": -51.50784725749125,
      "matcherColor": "#b68f5e"
     }
    ]
   }
  }
 },
 {
  "id": "kreis-13325",
  "colors": {
   "hexPalette": [
    "#9a9894",
    "#fffde9"
   ],
   "byNames": {
    "grey": [
     {
      "distanceToThreshold": -1,
      "matcherColor": "#888"
     }
    ]
   },
   "byNamesRejected": {
    "red": [
     {
      "distanceToThreshold": -228.80108191427638,
      "matcherColor": "#fe3940"
     }
    ],
    "blue": [
     {
      "distanceToThreshold": -122.36847580589225,
      "matcherColor": "#5596c3"
     }
    ],
    "green": [
     {
      "distanceToThreshold": -255.42437667310048,
      "matcherColor": "#0f0"
     }
    ],
    "gold": [
     {
      "distanceToThreshold": -131.27205755154097,
      "matcherColor": "#bfa14e"
     }
    ]
   }
  }
 },
 {
  "id": "land-13327",
  "colors": {
   "hexPalette": [
    "#f1442a",
    "#0296cd",
    "#000000",
    "#ffffff"
   ],
   "byNames": {
    "red": [
     {
      "distanceToThreshold": 2.179144513512888,
      "matcherColor": "#fe3940"
     }
    ],
    "blue": [
     {
      "distanceToThreshold": 20.974367397824288,
      "matcherColor": "#1d7dc0"
     }
    ],
    "black": [
     {
      "distanceToThreshold": -1,
      "matcherColor": "#000"
     }
    ],
    "white": [
     {
      "distanceToThreshold": -1,
      "matcherColor": "#fff"
     }
    ]
   },
   "byNamesRejected": {
    "blue": [
     {
      "distanceToThreshold": -153.3859464492239,
      "matcherColor": "#5596c3"
     }
    ],
    "green": [
     {
      "distanceToThreshold": -72.53301475481496,
      "matcherColor": "#00824a"
     }
    ],
    "gold": [
     {
      "distanceToThreshold": -151.5892246783848,
      "matcherColor": "#b68f5e"
     }
    ],
    "red": [
     {
      "distanceToThreshold": -273.37105992497044,
      "matcherColor": "#fe3940"
     }
    ]
   }
  },
  "markers": {
   "animals": [
    "lion"
   ]
  }
 },
 {
  "id": "kreis-13329",
  "colors": {
   "hexPalette": [
    "#fdd017",
    "#005ebe",
    "#8f908d",
    "#ffffff",
    "#373632"
   ],
   "byNames": {
    "gold": [
     {
      "distanceToThreshold": 22.410107741574997,
      "matcherColor": "#e6c633"
     }
    ],
    "blue": [
     {
      "distanceToThreshold": 49.704369859013,
      "matcherColor": "#0059c7"
     }
    ],
    "grey": [
     {
      "distanceToThreshold": -1,
      "matcherColor": "#888"
     }
    ],
    "white": [
     {
      "distanceToThreshold": -1,
      "matcherColor": "#fff"
     }
    ]
   },
   "byNamesRejected": {
    "red": [
     {
      "distanceToThreshold": -251.6036791110738,
      "matcherColor": "#f00"
     }
    ],
    "blue": [
     {
      "distanceToThreshold": -167.329739416836,
      "matcherColor": "#5596c3"
     }
    ],
    "green": [
     {
      "distanceToThreshold": -61.45781160551181,
      "matcherColor": "#00824a"
     }
    ],
    "gold": [
     {
      "distanceToThreshold": -151.52068456772733,
      "matcherColor": "#b68f5e"
     }
    ]
   }
  },
  "markers": {
   "animals": [
    "lion"
   ],
   "items": [
    "tree",
    "flower",
    "rose"
   ]
  }
 },
 {
  "id": "kreis-13330",
  "colors": {
   "hexPalette": [
    "#eae338",
    "#d41418",
    "#636365",
    "#000000",
    "#ffffff"
   ],
   "byNames": {
    "gold": [
     {
      "distanceToThreshold": 30.301515190165006,
      "matcherColor": "#e6c633"
     }
    ],
    "red": [
     {
      "distanceToThreshold": 26.849270936326754,
      "matcherColor": "#f00"
     }
    ],
    "grey": [
     {
      "distanceToThreshold": -1,
      "matcherColor": "#888"
     }
    ],
    "black": [
     {
      "distanceToThreshold": -1,
      "matcherColor": "#000"
     }
    ],
    "white": [
     {
      "distanceToThreshold": -1,
      "matcherColor": "#fff"
     }
    ]
   },
   "byNamesRejected": {
    "red": [
     {
      "distanceToThreshold": -141.35927170713583,
      "matcherColor": "#fe3940"
     }
    ],
    "blue": [
     {
      "distanceToThreshold": -147.61984490891038,
      "matcherColor": "#243b7f"
     }
    ],
    "green": [
     {
      "distanceToThreshold": -141.95042573791494,
      "matcherColor": "#006f00"
     }
    ],
    "gold": [
     {
      "distanceToThreshold": -84.66858677681205,
      "matcherColor": "#b68f5e"
     }
    ]
   }
  },
  "markers": {
   "animals": [
    "eagle",
    "bird"
   ],
   "items": [
    "wheel"
   ]
  }
 },
 {
  "id": "kreis-13331",
  "colors": {
   "hexPalette": [
    "#f02c2c",
    "#1e1f1c",
    "#828282",
    "#ffffff"
   ],
   "byNames": {
    "red": [
     {
      "distanceToThreshold": 15.992187976778965,
      "matcherColor": "#f00"
     }
    ],
    "grey": [
     {
      "distanceToThreshold": -1,
      "matcherColor": "#888"
     }
    ],
    "white": [
     {
      "distanceToThreshold": -1,
      "matcherColor": "#fff"
     }
    ]
   },
   "byNamesRejected": {
    "blue": [
     {
      "distanceToThreshold": -159.23731434224422,
      "matcherColor": "#2e3192"
     }
    ],
    "green": [
     {
      "distanceToThreshold": -163.03161857759991,
      "matcherColor": "#006f00"
     }
    ],
    "gold": [
     {
      "distanceToThreshold": -65.15989773086265,
      "matcherColor": "#b68f5e"
     }
    ]
   }
  },
  "markers": {
   "items": [
    "walls"
   ]
  }
 },
 {
  "id": "kreis-13332",
  "colors": {
   "hexPalette": [
    "#fcdd08",
    "#d01d35",
    "#949494",
    "#ffffff",
    "#000000"
   ],
   "byNames": {
    "gold": [
     {
      "distanceToThreshold": 14.94290371408379,
      "matcherColor": "#ffff00"
     }
    ],
    "red": [
     {
      "distanceToThreshold": 3.45589506696156,
      "matcherColor": "#f00"
     }
    ],
    "grey": [
     {
      "distanceToThreshold": -1,
      "matcherColor": "#888"
     }
    ],
    "white": [
     {
      "distanceToThreshold": -1,
      "matcherColor": "#fff"
     }
    ],
    "black": [
     {
      "distanceToThreshold": -1,
      "matcherColor": "#000"
     }
    ]
   },
   "byNamesRejected": {
    "red": [
     {
      "distanceToThreshold": -141.16509670379727,
      "matcherColor": "#f00"
     }
    ],
    "blue": [
     {
      "distanceToThreshold": -127.86431273661319,
      "matcherColor": "#2e3192"
     }
    ],
    "green": [
     {
      "distanceToThreshold": -139.77597785669414,
      "matcherColor": "#006f00"
     }
    ],
    "gold": [
     {
      "distanceToThreshold": -63.90722335683259,
      "matcherColor": "#b68f5e"
     }
    ]
   }
  },
  "markers": {
   "animals": [
    "crane",
    "lion",
    "bird"
   ]
  }
 },
 {
  "id": "kreis-13333",
  "colors": {
   "hexPalette": [
    "#fcdd08",
    "#da131b",
    "#636566",
    "#ffffff",
    "#000000"
   ],
   "byNames": {
    "gold": [
     {
      "distanceToThreshold": 14.94290371408379,
      "matcherColor": "#ffff00"
     }
    ],
    "red": [
     {
      "distanceToThreshold": 30.41169492713025,
      "matcherColor": "#f00"
     }
    ],
    "grey": [
     {
      "distanceToThreshold": -1,
      "matcherColor": "#888"
     }
    ],
    "white": [
     {
      "distanceToThreshold": -1,
      "matcherColor": "#fff"
     }
    ],
    "black": [
     {
      "distanceToThreshold": -1,
      "matcherColor": "#000"
     }
    ]
   },
   "byNamesRejected": {
    "red": [
     {
      "distanceToThreshold": -141.16509670379727,
      "matcherColor": "#f00"
     }
    ],
    "blue": [
     {
      "distanceToThreshold": -151.29363454680788,
      "matcherColor": "#2e3192"
     }
    ],
    "green": [
     {
      "distanceToThreshold": -148.15331196521285,
      "matcherColor": "#006f00"
     }
    ],
    "gold": [
     {
      "distanceToThreshold": -85.46820958546235,
      "matcherColor": "#b68f5e"
     }
    ]
   }
  },
  "markers": {
   "animals": [
    "rooster",
    "lion",
    "bird"
   ]
  }
 },
 {
  "id": "kreis-13334",
  "colors": {
   "hexPalette": [
    "#fcdd08",
    "#0f47af",
    "#81731d",
    "#010101"
   ],
   "byNames": {
    "gold": [
     {
      "distanceToThreshold": 14.94290371408379,
      "matcherColor": "#ffff00"
     }
    ],
    "blue": [
     {
      "distanceToThreshold": 26.458980337503156,
      "matcherColor": "#0059c7"
     }
    ],
    "black": [
     {
      "distanceToThreshold": -1,
      "matcherColor": "#000"
     }
    ]
   },
   "byNamesRejected": {
    "red": [
     {
      "distanceToThreshold": -93.0375681752376,
      "matcherColor": "#f00"
     }
    ],
    "blue": [
     {
      "distanceToThreshold": -86.24978632463024,
      "matcherColor": "#243b7f"
     }
    ],
    "green": [
     {
      "distanceToThreshold": -42.280006047777306,
      "matcherColor": "#006f00"
     }
    ],
    "gold": [
     {
      "distanceToThreshold": -28.41945487278238,
      "matcherColor": "#b68f5e"
     }
    ]
   }
  },
  "markers": {
   "animals": [
    "eagle",
    "rooster",
    "lion",
    "bird"
   ]
  }
 },
 {
  "id": "kreis-13335",
  "colors": {
   "hexPalette": [
    "#fdd017",
    "#1fb53c",
    "#005ebe",
    "#4b3700",
    "#9f7879",
    "#ffffff"
   ],
   "byNames": {
    "gold": [
     {
      "distanceToThreshold": 17.7270772243035,
      "matcherColor": "#b68f5e"
     }
    ],
    "green": [
     {
      "distanceToThreshold": 17.4559052276347,
      "matcherColor": "#07923f"
     }
    ],
    "blue": [
     {
      "distanceToThreshold": 49.704369859013,
      "matcherColor": "#0059c7"
     }
    ],
    "white": [
     {
      "distanceToThreshold": -1,
      "matcherColor": "#fff"
     }
    ]
   },
   "byNamesRejected": {
    "red": [
     {
      "distanceToThreshold": -97.44802862343536,
      "matcherColor": "#fe3940"
     }
    ],
    "blue": [
     {
      "distanceToThreshold": -28.86689120205463,
      "matcherColor": "#5596c3"
     }
    ],
    "green": [
     {
      "distanceToThreshold": -104.75436261295178,
      "matcherColor": "#07923f"
     }
    ],
    "gold": [
     {
      "distanceToThreshold": -107.41863695538797,
      "matcherColor": "#b68f5e"
     }
    ]
   }
  },
  "markers": {
   "animals": [
    "lion"
   ]
  }
 },
 {
  "id": "kreis-13336",
  "colors": {
   "hexPalette": [
    "#fcdd08",
    "#da131b",
    "#898687",
    "#000200",
    "#ffffff"
   ],
   "byNames": {
    "gold": [
     {
      "distanceToThreshold": 14.94290371408379,
      "matcherColor": "#ffff00"
     }
    ],
    "red": [
     {
      "distanceToThreshold": 30.41169492713025,
      "matcherColor": "#f00"
     }
    ],
    "grey": [
     {
      "distanceToThreshold": -1,
      "matcherColor": "#888"
     }
    ],
    "black": [
     {
      "distanceToThreshold": -1,
      "matcherColor": "#000"
     }
    ],
    "white": [
     {
      "distanceToThreshold": -1,
      "matcherColor": "#fff"
     }
    ]
   },
   "byNamesRejected": {
    "red": [
     {
      "distanceToThreshold": -141.16509670379727,
      "matcherColor": "#f00"
     }
    ],
    "blue": [
     {
      "distanceToThreshold": -151.29363454680788,
      "matcherColor": "#2e3192"
     }
    ],
    "green": [
     {
      "distanceToThreshold": -148.15331196521285,
      "matcherColor": "#006f00"
     }
    ],
    "gold": [
     {
      "distanceToThreshold": -85.46820958546235,
      "matcherColor": "#b68f5e"
     }
    ]
   }
  },
  "markers": {
   "items": [
    "tree"
   ]
  }
 },
 {
  "id": "kreis-13337",
  "colors": {
   "hexPalette": [
    "#fbd117",
    "#ffffff",
    "#2b2b29"
   ],
   "byNames": {
    "gold": [
     {
      "distanceToThreshold": 23.31212734431172,
      "matcherColor": "#e6c633"
     }
    ],
    "white": [
     {
      "distanceToThreshold": -1,
      "matcherColor": "#fff"
     }
    ],
    "grey": [
     {
      "distanceToThreshold": -1,
      "matcherColor": "#888"
     }
    ]
   },
   "byNamesRejected": {
    "red": [
     {
      "distanceToThreshold": -127.46110630882791,
      "matcherColor": "#fe3940"
     }
    ],
    "blue": [
     {
      "distanceToThreshold": -166.2133221415933,
      "matcherColor": "#5596c3"
     }
    ],
    "green": [
     {
      "distanceToThreshold": -166.21475367355407,
      "matcherColor": "#0f0"
     }
    ]
   }
  },
  "markers": {
   "animals": [
    "lion"
   ],
   "items": [
    "heart"
   ]
  }
 },
 {
  "id": "kreis-13338",
  "colors": {
   "hexPalette": [
    "#db131e",
    "#fcdd0a",
    "#ffffff",
    "#000000"
   ],
   "byNames": {
    "red": [
     {
      "distanceToThreshold": 29.433212480917874,
      "matcherColor": "#f00"
     }
    ],
    "gold": [
     {
      "distanceToThreshold": 14.433161512442524,
      "matcherColor": "#ffff00"
     }
    ],
    "white": [
     {
      "distanceToThreshold": -1,
      "matcherColor": "#fff"
     }
    ],
    "black": [
     {
      "distanceToThreshold": -1,
      "matcherColor": "#000"
     }
    ]
   },
   "byNamesRejected": {
    "blue": [
     {
      "distanceToThreshold": -179.1428177665744,
      "matcherColor": "#5596c3"
     }
    ],
    "green": [
     {
      "distanceToThreshold": -164.47986167867978,
      "matcherColor": "#0f0"
     }
    ],
    "gold": [
     {
      "distanceToThreshold": -84.3641229668923,
      "matcherColor": "#b68f5e"
     }
    ],
    "red": [
     {
      "distanceToThreshold": -141.24646889837587,
      "matcherColor": "#f00"
     }
    ]
   }
  },
  "markers": {
   "animals": [
    "lion"
   ],
   "items": [
    "crown"
   ]
  }
 },
 {
  "id": "kreis-13339",
  "colors": {
   "hexPalette": [
    "#fdd017",
    "#2b2b29"
   ],
   "byNames": {
    "gold": [
     {
      "distanceToThreshold": 22.410107741574997,
      "matcherColor": "#e6c633"
     }
    ],
    "grey": [
     {
      "distanceToThreshold": -1,
      "matcherColor": "#888"
     }
    ]
   },
   "byNamesRejected": {
    "red": [
     {
      "distanceToThreshold": -126.47044449352089,
      "matcherColor": "#fe3940"
     }
    ],
    "blue": [
     {
      "distanceToThreshold": -167.329739416836,
      "matcherColor": "#5596c3"
     }
    ],
    "green": [
     {
      "distanceToThreshold": -168.35440774254266,
      "matcherColor": "#0f0"
     }
    ]
   }
  },
  "markers": {
   "animals": [
    "eagle",
    "bird"
   ],
   "items": [
    "cross"
   ]
  }
 },
 {
  "id": "kreis-13340",
  "colors": {
   "hexPalette": [
    "#fdd017",
    "#005ebe",
    "#8f9477",
    "#ffffff",
    "#2b2b29"
   ],
   "byNames": {
    "gold": [
     {
      "distanceToThreshold": 13.406008971113025,
      "matcherColor": "#b68f5e"
     }
    ],
    "blue": [
     {
      "distanceToThreshold": 49.704369859013,
      "matcherColor": "#0059c7"
     }
    ],
    "white": [
     {
      "distanceToThreshold": -1,
      "matcherColor": "#fff"
     }
    ],
    "grey": [
     {
      "distanceToThreshold": -1,
      "matcherColor": "#888"
     }
    ]
   },
   "byNamesRejected": {
    "red": [
     {
      "distanceToThreshold": -123.71076735219299,
      "matcherColor": "#fe3940"
     }
    ],
    "blue": [
     {
      "distanceToThreshold": -15.62426470305536,
      "matcherColor": "#5596c3"
     }
    ],
    "green": [
     {
      "distanceToThreshold": -87.09180806557515,
      "matcherColor": "#07923f"
     }
    ],
    "gold": [
     {
      "distanceToThreshold": -151.52068456772733,
      "matcherColor": "#b68f5e"
     }
    ]
   }
  },
  "markers": {
   "animals": [
    "rooster",
    "lion",
    "bird"
   ]
  }
 },
 {
  "id": "kreis-13341",
  "colors": {
   "hexPalette": [
    "#fdd017",
    "#005fbe",
    "#a49f9f",
    "#ffffff",
    "#2b2b29"
   ],
   "byNames": {
    "gold": [
     {
      "distanceToThreshold": 22.410107741574997,
      "matcherColor": "#e6c633"
     }
    ],
    "blue": [
     {
      "distanceToThreshold": 49.18334617360803,
      "matcherColor": "#0059c7"
     }
    ],
    "grey": [
     {
      "distanceToThreshold": -1,
      "matcherColor": "#888"
     }
    ],
    "white": [
     {
      "distanceToThreshold": -1,
      "matcherColor": "#fff"
     }
    ]
   },
   "byNamesRejected": {
    "red": [
     {
      "distanceToThreshold": -251.88853550552182,
      "matcherColor": "#f00"
     }
    ],
    "blue": [
     {
      "distanceToThreshold": -167.329739416836,
      "matcherColor": "#5596c3"
     }
    ],
    "green": [
     {
      "distanceToThreshold": -61.165176515366824,
      "matcherColor": "#00824a"
     }
    ],
    "gold": [
     {
      "distanceToThreshold": -151.29126815843574,
      "matcherColor": "#b68f5e"
     }
    ]
   }
  },
  "markers": {
   "animals": [
    "lion"
   ],
   "items": [
    "wheel"
   ]
  }
 },
 {
  "id": "kreis-13342",
  "colors": {
   "hexPalette": [
    "#ffdd00",
    "#ed1d26",
    "#0166b3",
    "#a9a9a9",
    "#ffffff",
    "#000000"
   ],
   "byNames": {
    "gold": [
     {
      "distanceToThreshold": 16,
      "matcherColor": "#ffff00"
     }
    ],
    "red": [
     {
      "distanceToThreshold": 28.921628843511463,
      "matcherColor": "#f00"
     }
    ],
    "blue": [
     {
      "distanceToThreshold": 36.125327227373354,
      "matcherColor": "#0059c7"
     }
    ],
    "grey": [
     {
      "distanceToThreshold": -1,
      "matcherColor": "#888"
     }
    ],
    "white": [
     {
      "distanceToThreshold": -1,
      "matcherColor": "#fff"
     }
    ],
    "black": [
     {
      "distanceToThreshold": -1,
      "matcherColor": "#000"
     }
    ]
   },
   "byNamesRejected": {
    "red": [
     {
      "distanceToThreshold": -247.04892600343453,
      "matcherColor": "#f00"
     }
    ],
    "blue": [
     {
      "distanceToThreshold": -160.32929900492127,
      "matcherColor": "#2e3192"
     }
    ],
    "green": [
     {
      "distanceToThreshold": -48.673823895177264,
      "matcherColor": "#00824a"
     }
    ],
    "gold": [
     {
      "distanceToThreshold": -144.12496172687946,
      "matcherColor": "#b68f5e"
     }
    ]
   }
  },
  "markers": {
   "animals": [
    "lion"
   ]
  }
 },
 {
  "id": "kreis-13343",
  "colors": {
   "hexPalette": [
    "#f4d018",
    "#035cbe",
    "#988c94",
    "#ffffff",
    "#2b2b29"
   ],
   "byNames": {
    "gold": [
     {
      "distanceToThreshold": 27.984378812835757,
      "matcherColor": "#e6c633"
     }
    ],
    "blue": [
     {
      "distanceToThreshold": 50.0501256289338,
      "matcherColor": "#0059c7"
     }
    ],
    "grey": [
     {
      "distanceToThreshold": -1,
      "matcherColor": "#888"
     }
    ],
    "white": [
     {
      "distanceToThreshold": -1,
      "matcherColor": "#fff"
     }
    ]
   },
   "byNamesRejected": {
    "red": [
     {
      "distanceToThreshold": -248.7369769283644,
      "matcherColor": "#f00"
     }
    ],
    "blue": [
     {
      "distanceToThreshold": -160.5950955443606,
      "matcherColor": "#5596c3"
     }
    ],
    "green": [
     {
      "distanceToThreshold": -62.10241602851272,
      "matcherColor": "#00824a"
     }
    ],
    "gold": [
     {
      "distanceToThreshold": -149.42301688209918,
      "matcherColor": "#b68f5e"
     }
    ]
   }
  },
  "markers": {
   "animals": [
    "eagle",
    "deer",
    "lion",
    "bird"
   ],
   "items": [
    "wheel"
   ]
  }
 },
 {
  "id": "kreis-13344",
  "colors": {
   "hexPalette": [
    "#fdd017",
    "#005ebe",
    "#88866b",
    "#2b2b29",
    "#ffffff"
   ],
   "byNames": {
    "gold": [
     {
      "distanceToThreshold": 11.358453971938765,
      "matcherColor": "#b68f5e"
     }
    ],
    "blue": [
     {
      "distanceToThreshold": 49.704369859013,
      "matcherColor": "#0059c7"
     }
    ],
    "grey": [
     {
      "distanceToThreshold": -1,
      "matcherColor": "#888"
     }
    ],
    "white": [
     {
      "distanceToThreshold": -1,
      "matcherColor": "#fff"
     }
    ]
   },
   "byNamesRejected": {
    "red": [
     {
      "distanceToThreshold": -117.31598691248686,
      "matcherColor": "#fe3940"
     }
    ],
    "blue": [
     {
      "distanceToThreshold": -22.96115772464877,
      "matcherColor": "#5596c3"
     }
    ],
    "green": [
     {
      "distanceToThreshold": -76.82470537150812,
      "matcherColor": "#07923f"
     }
    ],
    "gold": [
     {
      "distanceToThreshold": -151.52068456772733,
      "matcherColor": "#b68f5e"
     }
    ]
   }
  },
  "markers": {
   "animals": [
    "rooster",
    "lion",
    "bird"
   ],
   "items": [
    "cross"
   ]
  }
 },
 {
  "id": "kreis-13345",
  "colors": {
   "hexPalette": [
    "#f9de0a",
    "#da131b",
    "#6c6c6c",
    "#ffffff",
    "#000000"
   ],
   "byNames": {
    "gold": [
     {
      "distanceToThreshold": 15,
      "matcherColor": "#ffff00"
     }
    ],
    "red": [
     {
      "distanceToThreshold": 30.41169492713025,
      "matcherColor": "#f00"
     }
    ],
    "grey": [
     {
      "distanceToThreshold": -1,
      "matcherColor": "#888"
     }
    ],
    "white": [
     {
      "distanceToThreshold": -1,
      "matcherColor": "#fff"
     }
    ],
    "black": [
     {
      "distanceToThreshold": -1,
      "matcherColor": "#000"
     }
    ]
   },
   "byNamesRejected": {
    "red": [
     {
      "distanceToThreshold": -142.30609528305786,
      "matcherColor": "#f00"
     }
    ],
    "blue": [
     {
      "distanceToThreshold": -151.29363454680788,
      "matcherColor": "#2e3192"
     }
    ],
    "green": [
     {
      "distanceToThreshold": -148.15331196521285,
      "matcherColor": "#006f00"
     }
    ],
    "gold": [
     {
      "distanceToThreshold": -85.46820958546235,
      "matcherColor": "#b68f5e"
     }
    ]
   }
  },
  "markers": {
   "animals": [
    "lion"
   ],
   "items": [
    "wheel"
   ]
  }
 },
 {
  "id": "city-13346",
  "colors": {
   "hexPalette": [
    "#ef2223",
    "#959593",
    "#000000",
    "#ffffff"
   ],
   "byNames": {
    "red": [
     {
      "distanceToThreshold": 28.64827169412893,
      "matcherColor": "#f00"
     }
    ],
    "grey": [
     {
      "distanceToThreshold": -1,
      "matcherColor": "#888"
     }
    ],
    "black": [
     {
      "distanceToThreshold": -1,
      "matcherColor": "#000"
     }
    ],
    "white": [
     {
      "distanceToThreshold": -1,
      "matcherColor": "#fff"
     }
    ]
   },
   "byNamesRejected": {
    "blue": [
     {
      "distanceToThreshold": -163.14793299513218,
      "matcherColor": "#2e3192"
     }
    ],
    "green": [
     {
      "distanceToThreshold": -163.52514668174436,
      "matcherColor": "#006f00"
     }
    ],
    "gold": [
     {
      "distanceToThreshold": -76.42213896578517,
      "matcherColor": "#b68f5e"
     }
    ]
   }
  },
  "markers": {
   "items": [
    "saint",
    "wheel"
   ]
  }
 },
 {
  "id": "city-13347",
  "colors": {
   "hexPalette": [
    "#f5cd1d",
    "#959794",
    "#ffffff",
    "#2c2d2a"
   ],
   "byNames": {
    "gold": [
     {
      "distanceToThreshold": 32.46820020412759,
      "matcherColor": "#e6c633"
     }
    ],
    "grey": [
     {
      "distanceToThreshold": -1,
      "matcherColor": "#888"
     }
    ],
    "white": [
     {
      "distanceToThreshold": -1,
      "matcherColor": "#fff"
     }
    ]
   },
   "byNamesRejected": {
    "red": [
     {
      "distanceToThreshold": -122.34828518890524,
      "matcherColor": "#fe3940"
     }
    ],
    "blue": [
     {
      "distanceToThreshold": -157.02531510368254,
      "matcherColor": "#5596c3"
     }
    ],
    "green": [
     {
      "distanceToThreshold": -161.726041561059,
      "matcherColor": "#0f0"
     }
    ]
   }
  },
  "markers": {
   "animals": [
    "lion",
    "peacock",
    "bird"
   ]
  }
 },
 {
  "id": "city-13348",
  "colors": {
   "hexPalette": [
    "#ffdb0a",
    "#747474",
    "#000000",
    "#ffffff"
   ],
   "byNames": {
    "gold": [
     {
      "distanceToThreshold": 12.636916615461189,
      "matcherColor": "#ffff00"
     }
    ],
    "grey": [
     {
      "distanceToThreshold": -1,
      "matcherColor": "#888"
     }
    ],
    "black": [
     {
      "distanceToThreshold": -1,
      "matcherColor": "#000"
     }
    ],
    "white": [
     {
      "distanceToThreshold": -1,
      "matcherColor": "#fff"
     }
    ]
   },
   "byNamesRejected": {
    "red": [
     {
      "distanceToThreshold": -139.22819161777528,
      "matcherColor": "#f00"
     }
    ],
    "blue": [
     {
      "distanceToThreshold": -180.54941949657075,
      "matcherColor": "#5596c3"
     }
    ],
    "green": [
     {
      "distanceToThreshold": -167.722719215827,
      "matcherColor": "#0f0"
     }
    ]
   }
  },
  "markers": {
   "animals": [
    "lion",
    "bird",
    "dragon"
   ],
   "items": [
    "grape",
    "angel"
   ]
  }
 },
 {
  "id": "city-13349",
  "colors": {
   "hexPalette": [
    "#f4df10",
    "#0e49a0",
    "#da121d",
    "#120400",
    "#a2a2a2",
    "#ffffff"
   ],
   "byNames": {
    "gold": [
     {
      "distanceToThreshold": 14.767268488405435,
      "matcherColor": "#e6c633"
     }
    ],
    "blue": [
     {
      "distanceToThreshold": 17.940518310373818,
      "matcherColor": "#243b7f"
     }
    ],
    "red": [
     {
      "distanceToThreshold": 29.66114820538712,
      "matcherColor": "#f00"
     }
    ],
    "black": [
     {
      "distanceToThreshold": -1,
      "matcherColor": "#000"
     }
    ],
    "grey": [
     {
      "distanceToThreshold": -1,
      "matcherColor": "#888"
     }
    ],
    "white": [
     {
      "distanceToThreshold": -1,
      "matcherColor": "#fff"
     }
    ]
   },
   "byNamesRejected": {
    "red": [
     {
      "distanceToThreshold": -218.34543737084368,
      "matcherColor": "#f00"
     }
    ],
    "blue": [
     {
      "distanceToThreshold": -150.3188056261256,
      "matcherColor": "#2e3192"
     }
    ],
    "green": [
     {
      "distanceToThreshold": -148.77604569973096,
      "matcherColor": "#006f00"
     }
    ],
    "gold": [
     {
      "distanceToThreshold": -85.41664278891878,
      "matcherColor": "#b68f5e"
     }
    ]
   }
  },
  "markers": {
   "animals": [
    "rooster",
    "bird"
   ],
   "items": [
    "walls"
   ]
  }
 },
 {
  "id": "city-13350",
  "colors": {
   "hexPalette": [
    "#f9d001",
    "#c32e25",
    "#000000"
   ],
   "byNames": {
    "gold": [
     {
      "distanceToThreshold": 5.584928558348835,
      "matcherColor": "#e6c633"
     }
    ],
    "black": [
     {
      "distanceToThreshold": -1,
      "matcherColor": "#000"
     }
    ]
   },
   "byNamesRejected": {
    "red": [
     {
      "distanceToThreshold": -4.172442046075858,
      "matcherColor": "#f00"
     }
    ],
    "blue": [
     {
      "distanceToThreshold": -123.16659084014202,
      "matcherColor": "#243b7f"
     }
    ],
    "green": [
     {
      "distanceToThreshold": -118.85162197119755,
      "matcherColor": "#006f00"
     }
    ],
    "gold": [
     {
      "distanceToThreshold": -53.25634640054393,
      "matcherColor": "#b68f5e"
     }
    ]
   }
  },
  "markers": {
   "animals": [
    "eagle",
    "lion",
    "bird"
   ],
   "items": [
    "wheel",
    "heart"
   ]
  }
 },
 {
  "id": "city-13351",
  "colors": {
   "hexPalette": [
    "#ef2223",
    "#959593",
    "#000000",
    "#ffffff"
   ],
   "byNames": {
    "red": [
     {
      "distanceToThreshold": 28.64827169412893,
      "matcherColor": "#f00"
     }
    ],
    "grey": [
     {
      "distanceToThreshold": -1,
      "matcherColor": "#888"
     }
    ],
    "black": [
     {
      "distanceToThreshold": -1,
      "matcherColor": "#000"
     }
    ],
    "white": [
     {
      "distanceToThreshold": -1,
      "matcherColor": "#fff"
     }
    ]
   },
   "byNamesRejected": {
    "blue": [
     {
      "distanceToThreshold": -163.14793299513218,
      "matcherColor": "#2e3192"
     }
    ],
    "green": [
     {
      "distanceToThreshold": -163.52514668174436,
      "matcherColor": "#006f00"
     }
    ],
    "gold": [
     {
      "distanceToThreshold": -76.42213896578517,
      "matcherColor": "#b68f5e"
     }
    ]
   }
  },
  "markers": {
   "items": [
    "saint",
    "wheel"
   ]
  }
 },
 {
  "id": "city-13352",
  "colors": {
   "hexPalette": [
    "#f5cd1d",
    "#959794",
    "#ffffff",
    "#2c2d2a"
   ],
   "byNames": {
    "gold": [
     {
      "distanceToThreshold": 32.46820020412759,
      "matcherColor": "#e6c633"
     }
    ],
    "grey": [
     {
      "distanceToThreshold": -1,
      "matcherColor": "#888"
     }
    ],
    "white": [
     {
      "distanceToThreshold": -1,
      "matcherColor": "#fff"
     }
    ]
   },
   "byNamesRejected": {
    "red": [
     {
      "distanceToThreshold": -122.34828518890524,
      "matcherColor": "#fe3940"
     }
    ],
    "blue": [
     {
      "distanceToThreshold": -157.02531510368254,
      "matcherColor": "#5596c3"
     }
    ],
    "green": [
     {
      "distanceToThreshold": -161.726041561059,
      "matcherColor": "#0f0"
     }
    ]
   }
  }
 },
 {
  "id": "city-13353",
  "colors": {
   "hexPalette": [
    "#ffdb0a",
    "#747474",
    "#000000",
    "#ffffff"
   ],
   "byNames": {
    "gold": [
     {
      "distanceToThreshold": 12.636916615461189,
      "matcherColor": "#ffff00"
     }
    ],
    "grey": [
     {
      "distanceToThreshold": -1,
      "matcherColor": "#888"
     }
    ],
    "black": [
     {
      "distanceToThreshold": -1,
      "matcherColor": "#000"
     }
    ],
    "white": [
     {
      "distanceToThreshold": -1,
      "matcherColor": "#fff"
     }
    ]
   },
   "byNamesRejected": {
    "red": [
     {
      "distanceToThreshold": -139.22819161777528,
      "matcherColor": "#f00"
     }
    ],
    "blue": [
     {
      "distanceToThreshold": -180.54941949657075,
      "matcherColor": "#5596c3"
     }
    ],
    "green": [
     {
      "distanceToThreshold": -167.722719215827,
      "matcherColor": "#0f0"
     }
    ]
   }
  },
  "markers": {
   "animals": [
    "lion",
    "bird",
    "dragon"
   ],
   "items": [
    "grape",
    "angel"
   ]
  }
 },
 {
  "id": "city-13354",
  "colors": {
   "hexPalette": [
    "#f4df10",
    "#0e49a0",
    "#da121d",
    "#120400",
    "#a2a2a2",
    "#ffffff"
   ],
   "byNames": {
    "gold": [
     {
      "distanceToThreshold": 14.767268488405435,
      "matcherColor": "#e6c633"
     }
    ],
    "blue": [
     {
      "distanceToThreshold": 17.940518310373818,
      "matcherColor": "#243b7f"
     }
    ],
    "red": [
     {
      "distanceToThreshold": 29.66114820538712,
      "matcherColor": "#f00"
     }
    ],
    "black": [
     {
      "distanceToThreshold": -1,
      "matcherColor": "#000"
     }
    ],
    "grey": [
     {
      "distanceToThreshold": -1,
      "matcherColor": "#888"
     }
    ],
    "white": [
     {
      "distanceToThreshold": -1,
      "matcherColor": "#fff"
     }
    ]
   },
   "byNamesRejected": {
    "red": [
     {
      "distanceToThreshold": -218.34543737084368,
      "matcherColor": "#f00"
     }
    ],
    "blue": [
     {
      "distanceToThreshold": -150.3188056261256,
      "matcherColor": "#2e3192"
     }
    ],
    "green": [
     {
      "distanceToThreshold": -148.77604569973096,
      "matcherColor": "#006f00"
     }
    ],
    "gold": [
     {
      "distanceToThreshold": -85.41664278891878,
      "matcherColor": "#b68f5e"
     }
    ]
   }
  },
  "markers": {
   "animals": [
    "rooster",
    "bird"
   ],
   "items": [
    "walls"
   ]
  }
 },
 {
  "id": "city-13355",
  "colors": {
   "hexPalette": [
    "#f9d001",
    "#c32e25",
    "#000000"
   ],
   "byNames": {
    "gold": [
     {
      "distanceToThreshold": 5.584928558348835,
      "matcherColor": "#e6c633"
     }
    ],
    "black": [
     {
      "distanceToThreshold": -1,
      "matcherColor": "#000"
     }
    ]
   },
   "byNamesRejected": {
    "red": [
     {
      "distanceToThreshold": -4.172442046075858,
      "matcherColor": "#f00"
     }
    ],
    "blue": [
     {
      "distanceToThreshold": -123.16659084014202,
      "matcherColor": "#243b7f"
     }
    ],
    "green": [
     {
      "distanceToThreshold": -118.85162197119755,
      "matcherColor": "#006f00"
     }
    ],
    "gold": [
     {
      "distanceToThreshold": -53.25634640054393,
      "matcherColor": "#b68f5e"
     }
    ]
   }
  },
  "markers": {
   "animals": [
    "eagle",
    "lion",
    "bird"
   ],
   "items": [
    "wheel",
    "heart"
   ]
  }
 },
 {
  "id": "city-13356",
  "colors": {
   "hexPalette": [
    "#b29b68",
    "#38373e",
    "#ffffff"
   ],
   "byNames": {
    "gold": [
     {
      "distanceToThreshold": 43.8754845034029,
      "matcherColor": "#b68f5e"
     }
    ],
    "grey": [
     {
      "distanceToThreshold": -1,
      "matcherColor": "#888"
     }
    ],
    "white": [
     {
      "distanceToThreshold": -1,
      "matcherColor": "#fff"
     }
    ]
   },
   "byNamesRejected": {
    "red": [
     {
      "distanceToThreshold": -100.3073290340954,
      "matcherColor": "#fe3940"
     }
    ],
    "blue": [
     {
      "distanceToThreshold": -50.21136663133521,
      "matcherColor": "#5596c3"
     }
    ],
    "green": [
     {
      "distanceToThreshold": -116.07668783799858,
      "matcherColor": "#07923f"
     }
    ]
   }
  },
  "markers": {
   "items": [
    "cross",
    "wheel"
   ]
  }
 },
 {
  "id": "city-13357",
  "colors": {
   "hexPalette": [
    "#ec4b44",
    "#0b0105",
    "#969191",
    "#ffffff"
   ],
   "byNames": {
    "red": [
     {
      "distanceToThreshold": 4.231802546549748,
      "matcherColor": "#fe3940"
     }
    ],
    "black": [
     {
      "distanceToThreshold": -1,
      "matcherColor": "#000"
     }
    ],
    "grey": [
     {
      "distanceToThreshold": -1,
      "matcherColor": "#888"
     }
    ],
    "white": [
     {
      "distanceToThreshold": -1,
      "matcherColor": "#fff"
     }
    ]
   },
   "byNamesRejected": {
    "blue": [
     {
      "distanceToThreshold": -131.08055334397812,
      "matcherColor": "#5596c3"
     }
    ],
    "green": [
     {
      "distanceToThreshold": -158.22570374560325,
      "matcherColor": "#006f00"
     }
    ],
    "gold": [
     {
      "distanceToThreshold": -30.642153548997285,
      "matcherColor": "#b68f5e"
     }
    ]
   }
  },
  "markers": {
   "items": [
    "walls",
    "sword"
   ]
  }
 },
 {
  "id": "city-13358",
  "colors": {
   "hexPalette": [
    "#777415",
    "#18249e",
    "#a4a7a3",
    "#ffffff"
   ],
   "byNames": {
    "blue": [
     {
      "distanceToThreshold": 31.768811573013792,
      "matcherColor": "#2e3192"
     }
    ],
    "grey": [
     {
      "distanceToThreshold": -1,
      "matcherColor": "#888"
     }
    ],
    "white": [
     {
      "distanceToThreshold": -1,
      "matcherColor": "#fff"
     }
    ]
   },
   "byNamesRejected": {
    "red": [
     {
      "distanceToThreshold": -202.17193340231415,
      "matcherColor": "#f00"
     }
    ],
    "blue": [
     {
      "distanceToThreshold": -86.19849520429409,
      "matcherColor": "#243b7f"
     }
    ],
    "green": [
     {
      "distanceToThreshold": -68.32770550430644,
      "matcherColor": "#00824a"
     }
    ],
    "gold": [
     {
      "distanceToThreshold": -141.2684774126341,
      "matcherColor": "#b68f5e"
     }
    ]
   }
  }
 },
 {
  "id": "city-13359",
  "colors": {
   "hexPalette": [
    "#20212a",
    "#979797",
    "#ffffff"
   ],
   "byNames": {
    "grey": [
     {
      "distanceToThreshold": -1,
      "matcherColor": "#888"
     }
    ],
    "white": [
     {
      "distanceToThreshold": -1,
      "matcherColor": "#fff"
     }
    ]
   },
   "byNamesRejected": {}
  }
 },
 {
  "id": "city-13360",
  "colors": {
   "hexPalette": [
    "#ff0036",
    "#0530be",
    "#27001d",
    "#866f60",
    "#ffffff"
   ],
   "byNames": {
    "red": [
     {
      "distanceToThreshold": 26,
      "matcherColor": "#f00"
     }
    ],
    "blue": [
     {
      "distanceToThreshold": 17.7270772243035,
      "matcherColor": "#0059c7"
     }
    ],
    "gold": [
     {
      "distanceToThreshold": 2.2765212413527536,
      "matcherColor": "#b68f5e"
     }
    ],
    "white": [
     {
      "distanceToThreshold": -1,
      "matcherColor": "#fff"
     }
    ]
   },
   "byNamesRejected": {
    "blue": [
     {
      "distanceToThreshold": -37.14520903562382,
      "matcherColor": "#5596c3"
     }
    ],
    "green": [
     {
      "distanceToThreshold": -74.83931569865243,
      "matcherColor": "#006f00"
     }
    ],
    "gold": [
     {
      "distanceToThreshold": -152.4217502987865,
      "matcherColor": "#b68f5e"
     }
    ],
    "red": [
     {
      "distanceToThreshold": -105.42525613784159,
      "matcherColor": "#fe3940"
     }
    ]
   }
  },
  "markers": {
   "animals": [
    "eagle",
    "bird"
   ]
  }
 },
 {
  "id": "city-13361",
  "colors": {
   "hexPalette": [
    "#53b015",
    "#fe1c2f",
    "#5d3b7f",
    "#0e0f13",
    "#ffffff"
   ],
   "byNames": {
    "red": [
     {
      "distanceToThreshold": 25.28254391878219,
      "matcherColor": "#f00"
     }
    ],
    "blue": [
     {
      "distanceToThreshold": 8.32795726894475,
      "matcherColor": "#2e3192"
     }
    ],
    "black": [
     {
      "distanceToThreshold": -1,
      "matcherColor": "#000"
     }
    ],
    "white": [
     {
      "distanceToThreshold": -1,
      "matcherColor": "#fff"
     }
    ]
   },
   "byNamesRejected": {
    "red": [
     {
      "distanceToThreshold": -134.1354711391833,
      "matcherColor": "#f00"
     }
    ],
    "blue": [
     {
      "distanceToThreshold": -171.31363989181443,
      "matcherColor": "#2e3192"
     }
    ],
    "green": [
     {
      "distanceToThreshold": -68.44843323295152,
      "matcherColor": "#00824a"
     }
    ],
    "gold": [
     {
      "distanceToThreshold": -66.75172582651489,
      "matcherColor": "#b68f5e"
     }
    ]
   }
  }
 },
 {
  "id": "city-13362",
  "colors": {
   "hexPalette": [
    "#b29b68",
    "#38373e",
    "#ffffff"
   ],
   "byNames": {
    "gold": [
     {
      "distanceToThreshold": 43.8754845034029,
      "matcherColor": "#b68f5e"
     }
    ],
    "grey": [
     {
      "distanceToThreshold": -1,
      "matcherColor": "#888"
     }
    ],
    "white": [
     {
      "distanceToThreshold": -1,
      "matcherColor": "#fff"
     }
    ]
   },
   "byNamesRejected": {
    "red": [
     {
      "distanceToThreshold": -100.3073290340954,
      "matcherColor": "#fe3940"
     }
    ],
    "blue": [
     {
      "distanceToThreshold": -50.21136663133521,
      "matcherColor": "#5596c3"
     }
    ],
    "green": [
     {
      "distanceToThreshold": -116.07668783799858,
      "matcherColor": "#07923f"
     }
    ]
   }
  },
  "markers": {
   "items": [
    "cross",
    "wheel"
   ]
  }
 },
 {
  "id": "city-13363",
  "colors": {
   "hexPalette": [
    "#ec4b44",
    "#0b0105",
    "#969191",
    "#ffffff"
   ],
   "byNames": {
    "red": [
     {
      "distanceToThreshold": 4.231802546549748,
      "matcherColor": "#fe3940"
     }
    ],
    "black": [
     {
      "distanceToThreshold": -1,
      "matcherColor": "#000"
     }
    ],
    "grey": [
     {
      "distanceToThreshold": -1,
      "matcherColor": "#888"
     }
    ],
    "white": [
     {
      "distanceToThreshold": -1,
      "matcherColor": "#fff"
     }
    ]
   },
   "byNamesRejected": {
    "blue": [
     {
      "distanceToThreshold": -131.08055334397812,
      "matcherColor": "#5596c3"
     }
    ],
    "green": [
     {
      "distanceToThreshold": -158.22570374560325,
      "matcherColor": "#006f00"
     }
    ],
    "gold": [
     {
      "distanceToThreshold": -30.642153548997285,
      "matcherColor": "#b68f5e"
     }
    ]
   }
  },
  "markers": {
   "items": [
    "walls",
    "sword"
   ]
  }
 },
 {
  "id": "city-13364",
  "colors": {
   "hexPalette": [
    "#777415",
    "#18249e",
    "#a4a7a3",
    "#ffffff"
   ],
   "byNames": {
    "blue": [
     {
      "distanceToThreshold": 31.768811573013792,
      "matcherColor": "#2e3192"
     }
    ],
    "grey": [
     {
      "distanceToThreshold": -1,
      "matcherColor": "#888"
     }
    ],
    "white": [
     {
      "distanceToThreshold": -1,
      "matcherColor": "#fff"
     }
    ]
   },
   "byNamesRejected": {
    "red": [
     {
      "distanceToThreshold": -202.17193340231415,
      "matcherColor": "#f00"
     }
    ],
    "blue": [
     {
      "distanceToThreshold": -86.19849520429409,
      "matcherColor": "#243b7f"
     }
    ],
    "green": [
     {
      "distanceToThreshold": -68.32770550430644,
      "matcherColor": "#00824a"
     }
    ],
    "gold": [
     {
      "distanceToThreshold": -141.2684774126341,
      "matcherColor": "#b68f5e"
     }
    ]
   }
  }
 },
 {
  "id": "city-13365",
  "colors": {
   "hexPalette": [
    "#20212a",
    "#979797",
    "#ffffff"
   ],
   "byNames": {
    "grey": [
     {
      "distanceToThreshold": -1,
      "matcherColor": "#888"
     }
    ],
    "white": [
     {
      "distanceToThreshold": -1,
      "matcherColor": "#fff"
     }
    ]
   },
   "byNamesRejected": {}
  }
 },
 {
  "id": "city-13366",
  "colors": {
   "hexPalette": [
    "#ff0036",
    "#0530be",
    "#27001d",
    "#866f60",
    "#ffffff"
   ],
   "byNames": {
    "red": [
     {
      "distanceToThreshold": 26,
      "matcherColor": "#f00"
     }
    ],
    "blue": [
     {
      "distanceToThreshold": 17.7270772243035,
      "matcherColor": "#0059c7"
     }
    ],
    "gold": [
     {
      "distanceToThreshold": 2.2765212413527536,
      "matcherColor": "#b68f5e"
     }
    ],
    "white": [
     {
      "distanceToThreshold": -1,
      "matcherColor": "#fff"
     }
    ]
   },
   "byNamesRejected": {
    "blue": [
     {
      "distanceToThreshold": -37.14520903562382,
      "matcherColor": "#5596c3"
     }
    ],
    "green": [
     {
      "distanceToThreshold": -74.83931569865243,
      "matcherColor": "#006f00"
     }
    ],
    "gold": [
     {
      "distanceToThreshold": -152.4217502987865,
      "matcherColor": "#b68f5e"
     }
    ],
    "red": [
     {
      "distanceToThreshold": -105.42525613784159,
      "matcherColor": "#fe3940"
     }
    ]
   }
  },
  "markers": {
   "animals": [
    "eagle",
    "bird"
   ]
  }
 },
 {
  "id": "city-13367",
  "colors": {
   "hexPalette": [
    "#53b015",
    "#fe1c2f",
    "#5d3b7f",
    "#0e0f13",
    "#ffffff"
   ],
   "byNames": {
    "red": [
     {
      "distanceToThreshold": 25.28254391878219,
      "matcherColor": "#f00"
     }
    ],
    "blue": [
     {
      "distanceToThreshold": 8.32795726894475,
      "matcherColor": "#2e3192"
     }
    ],
    "black": [
     {
      "distanceToThreshold": -1,
      "matcherColor": "#000"
     }
    ],
    "white": [
     {
      "distanceToThreshold": -1,
      "matcherColor": "#fff"
     }
    ]
   },
   "byNamesRejected": {
    "red": [
     {
      "distanceToThreshold": -134.1354711391833,
      "matcherColor": "#f00"
     }
    ],
    "blue": [
     {
      "distanceToThreshold": -171.31363989181443,
      "matcherColor": "#2e3192"
     }
    ],
    "green": [
     {
      "distanceToThreshold": -68.44843323295152,
      "matcherColor": "#00824a"
     }
    ],
    "gold": [
     {
      "distanceToThreshold": -66.75172582651489,
      "matcherColor": "#b68f5e"
     }
    ]
   }
  }
 },
 {
  "id": "city-13368",
  "colors": {
   "hexPalette": [
    "#2d59b5",
    "#eb342d",
    "#ffffff",
    "#1c1c1c"
   ],
   "byNames": {
    "blue": [
     {
      "distanceToThreshold": 19.09767732756488,
      "matcherColor": "#1d7dc0"
     }
    ],
    "red": [
     {
      "distanceToThreshold": 8.382962920824482,
      "matcherColor": "#f00"
     }
    ],
    "white": [
     {
      "distanceToThreshold": -1,
      "matcherColor": "#fff"
     }
    ],
    "grey": [
     {
      "distanceToThreshold": -1,
      "matcherColor": "#888"
     }
    ]
   },
   "byNamesRejected": {
    "red": [
     {
      "distanceToThreshold": -211.17348780409247,
      "matcherColor": "#f00"
     }
    ],
    "green": [
     {
      "distanceToThreshold": -156.43660442393698,
      "matcherColor": "#006f00"
     }
    ],
    "gold": [
     {
      "distanceToThreshold": -56.15076409563564,
      "matcherColor": "#b68f5e"
     }
    ],
    "blue": [
     {
      "distanceToThreshold": -153.67498796405232,
      "matcherColor": "#5596c3"
     }
    ]
   }
  },
  "markers": {
   "animals": [
    "lion"
   ]
  }
 },
 {
  "id": "city-13369",
  "colors": {
   "hexPalette": [
    "#f3ce50",
    "#58834d",
    "#0e0e0e",
    "#ffffff"
   ],
   "byNames": {
    "gold": [
     {
      "distanceToThreshold": 27.22806078365212,
      "matcherColor": "#e6c633"
     }
    ],
    "black": [
     {
      "distanceToThreshold": -1,
      "matcherColor": "#000"
     }
    ],
    "white": [
     {
      "distanceToThreshold": -1,
      "matcherColor": "#fff"
     }
    ]
   },
   "byNamesRejected": {
    "red": [
     {
      "distanceToThreshold": -145.7852962440203,
      "matcherColor": "#f00"
     }
    ],
    "blue": [
     {
      "distanceToThreshold": -39.55751753863075,
      "matcherColor": "#5596c3"
     }
    ],
    "green": [
     {
      "distanceToThreshold": -23.55836283700154,
      "matcherColor": "#07923f"
     }
    ],
    "gold": [
     {
      "distanceToThreshold": -36.27564593395361,
      "matcherColor": "#b68f5e"
     }
    ]
   }
  },
  "markers": {
   "animals": [
    "heron",
    "bird"
   ]
  }
 },
 {
  "id": "city-13370",
  "colors": {
   "hexPalette": [
    "#e4211c",
    "#144dae",
    "#060915",
    "#a9a8ab",
    "#ffffff"
   ],
   "byNames": {
    "red": [
     {
      "distanceToThreshold": 28.9901970205726,
      "matcherColor": "#f00"
     }
    ],
    "blue": [
     {
      "distanceToThreshold": 25.809358005442483,
      "matcherColor": "#0059c7"
     }
    ],
    "black": [
     {
      "distanceToThreshold": -1,
      "matcherColor": "#000"
     }
    ],
    "grey": [
     {
      "distanceToThreshold": -1,
      "matcherColor": "#888"
     }
    ],
    "white": [
     {
      "distanceToThreshold": -1,
      "matcherColor": "#fff"
     }
    ]
   },
   "byNamesRejected": {
    "blue": [
     {
      "distanceToThreshold": -157.4948275247023,
      "matcherColor": "#2e3192"
     }
    ],
    "green": [
     {
      "distanceToThreshold": -54.9304137293519,
      "matcherColor": "#00824a"
     }
    ],
    "gold": [
     {
      "distanceToThreshold": -132.35384061671346,
      "matcherColor": "#b68f5e"
     }
    ],
    "red": [
     {
      "distanceToThreshold": -222.37394067611052,
      "matcherColor": "#f00"
     }
    ]
   }
  },
  "markers": {
   "animals": [
    "lion"
   ]
  }
 },
 {
  "id": "city-13371",
  "colors": {
   "hexPalette": [
    "#ef2a18",
    "#ffffff",
    "#07050f"
   ],
   "byNames": {
    "red": [
     {
      "distanceToThreshold": 29.049043188572014,
      "matcherColor": "#f00"
     }
    ],
    "white": [
     {
      "distanceToThreshold": -1,
      "matcherColor": "#fff"
     }
    ],
    "black": [
     {
      "distanceToThreshold": -1,
      "matcherColor": "#000"
     }
    ]
   },
   "byNamesRejected": {
    "blue": [
     {
      "distanceToThreshold": -168.26957747365284,
      "matcherColor": "#243b7f"
     }
    ],
    "green": [
     {
      "distanceToThreshold": -159.91598588325638,
      "matcherColor": "#006f00"
     }
    ],
    "gold": [
     {
      "distanceToThreshold": -75.46217184144066,
      "matcherColor": "#b68f5e"
     }
    ]
   }
  },
  "markers": {
   "animals": [
    "bear"
   ]
  }
 },
 {
  "id": "city-13372",
  "colors": {
   "hexPalette": [
    "#f2cf3b",
    "#585453",
    "#080305",
    "#ffffff"
   ],
   "byNames": {
    "gold": [
     {
      "distanceToThreshold": 43,
      "matcherColor": "#e6c633"
     }
    ],
    "grey": [
     {
      "distanceToThreshold": -1,
      "matcherColor": "#888"
     }
    ],
    "black": [
     {
      "distanceToThreshold": -1,
      "matcherColor": "#000"
     }
    ],
    "white": [
     {
      "distanceToThreshold": -1,
      "matcherColor": "#fff"
     }
    ]
   },
   "byNamesRejected": {
    "red": [
     {
      "distanceToThreshold": -120.56227947264878,
      "matcherColor": "#fe3940"
     }
    ],
    "blue": [
     {
      "distanceToThreshold": -135.39266468475662,
      "matcherColor": "#5596c3"
     }
    ],
    "green": [
     {
      "distanceToThreshold": -163.67104683033892,
      "matcherColor": "#0f0"
     }
    ]
   }
  },
  "markers": {
   "animals": [
    "lion"
   ],
   "items": [
    "crown"
   ]
  }
 },
 {
  "id": "city-13373",
  "colors": {
   "hexPalette": [
    "#fffd01",
    "#005bd9",
    "#3ca446",
    "#00130e",
    "#fdfdfd"
   ],
   "byNames": {
    "gold": [
     {
      "distanceToThreshold": 47.763932022500214,
      "matcherColor": "#ffff00"
     }
    ],
    "blue": [
     {
      "distanceToThreshold": 41.889229723725165,
      "matcherColor": "#0059c7"
     }
    ],
    "green": [
     {
      "distanceToThreshold": 3.590780895318183,
      "matcherColor": "#07923f"
     }
    ],
    "black": [
     {
      "distanceToThreshold": -1,
      "matcherColor": "#000"
     }
    ],
    "white": [
     {
      "distanceToThreshold": -1,
      "matcherColor": "#fff"
     }
    ]
   },
   "byNamesRejected": {
    "red": [
     {
      "distanceToThreshold": -184.23663636975095,
      "matcherColor": "#f00"
     }
    ],
    "blue": [
     {
      "distanceToThreshold": -48.24195881223898,
      "matcherColor": "#5596c3"
     }
    ],
    "green": [
     {
      "distanceToThreshold": -88.22280526288793,
      "matcherColor": "#00824a"
     }
    ],
    "gold": [
     {
      "distanceToThreshold": -66.09916732476864,
      "matcherColor": "#b68f5e"
     }
    ]
   }
  },
  "markers": {
   "animals": [
    "rooster",
    "bird"
   ]
  }
 },
 {
  "id": "city-13374",
  "colors": {
   "hexPalette": [
    "#fec249",
    "#ffffff",
    "#4e7c43"
   ],
   "byNames": {
    "gold": [
     {
      "distanceToThreshold": 27.197561066286546,
      "matcherColor": "#e6c633"
     }
    ],
    "white": [
     {
      "distanceToThreshold": -1,
      "matcherColor": "#fff"
     }
    ]
   },
   "byNamesRejected": {
    "red": [
     {
      "distanceToThreshold": -146.26091133909983,
      "matcherColor": "#f00"
     }
    ],
    "blue": [
     {
      "distanceToThreshold": -37.923439482077015,
      "matcherColor": "#243b7f"
     }
    ],
    "green": [
     {
      "distanceToThreshold": -13.643620160625417,
      "matcherColor": "#006f00"
     }
    ],
    "gold": [
     {
      "distanceToThreshold": -49.1146186356347,
      "matcherColor": "#b68f5e"
     }
    ]
   }
  },
  "markers": {
   "items": [
    "tree",
    "flower"
   ]
  }
 },
 {
  "id": "city-13375",
  "colors": {
   "hexPalette": [
    "#e1051b",
    "#719630",
    "#f0fd32",
    "#010808"
   ],
   "byNames": {
    "red": [
     {
      "distanceToThreshold": 39.33060118467449,
      "matcherColor": "#f00"
     }
    ],
    "gold": [
     {
      "distanceToThreshold": 4.089357006022546,
      "matcherColor": "#e6c633"
     }
    ],
    "black": [
     {
      "distanceToThreshold": -1,
      "matcherColor": "#000"
     }
    ]
   },
   "byNamesRejected": {
    "blue": [
     {
      "distanceToThreshold": -155.92159714617057,
      "matcherColor": "#5596c3"
     }
    ],
    "green": [
     {
      "distanceToThreshold": -155.161171477051,
      "matcherColor": "#0f0"
     }
    ],
    "gold": [
     {
      "distanceToThreshold": -23.22259308625273,
      "matcherColor": "#b68f5e"
     }
    ],
    "red": [
     {
      "distanceToThreshold": -166.99746191258404,
      "matcherColor": "#fe3940"
     }
    ]
   }
  }
 },
 {
  "id": "city-13376",
  "colors": {
   "hexPalette": [
    "#ec4645",
    "#719f57",
    "#ffffff"
   ],
   "byNames": {
    "red": [
     {
      "distanceToThreshold": 7.240386646517916,
      "matcherColor": "#fe3940"
     }
    ],
    "white": [
     {
      "distanceToThreshold": -1,
      "matcherColor": "#fff"
     }
    ]
   },
   "byNamesRejected": {
    "blue": [
     {
      "distanceToThreshold": -31.933015683488136,
      "matcherColor": "#5596c3"
     }
    ],
    "green": [
     {
      "distanceToThreshold": -49.45775440780794,
      "matcherColor": "#07923f"
     }
    ],
    "gold": [
     {
      "distanceToThreshold": -11.175838597096984,
      "matcherColor": "#b68f5e"
     }
    ],
    "red": [
     {
      "distanceToThreshold": -145.53916941811022,
      "matcherColor": "#fe3940"
     }
    ]
   }
  },
  "markers": {
   "animals": [
    "rooster",
    "bird"
   ]
  }
 },
 {
  "id": "city-13377",
  "colors": {
   "hexPalette": [
    "#fc2829",
    "#979497",
    "#151419",
    "#ffffff"
   ],
   "byNames": {
    "red": [
     {
      "distanceToThreshold": 22.641478401200054,
      "matcherColor": "#f00"
     }
    ],
    "grey": [
     {
      "distanceToThreshold": -1,
      "matcherColor": "#888"
     }
    ],
    "black": [
     {
      "distanceToThreshold": -1,
      "matcherColor": "#000"
     }
    ],
    "white": [
     {
      "distanceToThreshold": -1,
      "matcherColor": "#fff"
     }
    ]
   },
   "byNamesRejected": {
    "blue": [
     {
      "distanceToThreshold": -171.39144322986536,
      "matcherColor": "#2e3192"
     }
    ],
    "green": [
     {
      "distanceToThreshold": -175.0018867857359,
      "matcherColor": "#006f00"
     }
    ],
    "gold": [
     {
      "distanceToThreshold": -75.34400614729859,
      "matcherColor": "#b68f5e"
     }
    ]
   }
  },
  "markers": {
   "animals": [
    "lion"
   ],
   "items": [
    "tree"
   ]
  }
 }
]